app/bot_start.py
telegram_payment_bot/__init__.py
telegram_payment_bot/_version.py
telegram_payment_bot/payment_bot.py
telegram_payment_bot/auth_user/__init__.py
telegram_payment_bot/auth_user/authorized_users_getter.py
telegram_payment_bot/auth_user/authorized_users_list.py
telegram_payment_bot/auth_user/authorized_users_message_sender.py
telegram_payment_bot/bot/__init__.py
telegram_payment_bot/bot/bot_base.py
telegram_payment_bot/bot/bot_config.py
telegram_payment_bot/bot/bot_config_types.py
telegram_payment_bot/bot/bot_handlers_config.py
telegram_payment_bot/bot/bot_handlers_config_typing.py
telegram_payment_bot/command/__init__.py
telegram_payment_bot/command/command_base.py
telegram_payment_bot/command/command_data.py
telegram_payment_bot/command/command_dispatcher.py
telegram_payment_bot/command/commands.py
telegram_payment_bot/config/__init__.py
telegram_payment_bot/config/config_file_sections_loader.py
telegram_payment_bot/config/config_loader_ex.py
telegram_payment_bot/config/config_object.py
telegram_payment_bot/config/config_section_loader.py
telegram_payment_bot/config/config_sections_loader.py
telegram_payment_bot/config/config_typing.py
telegram_payment_bot/email/__init__.py
telegram_payment_bot/email/emailer_auth_types.py
telegram_payment_bot/email/smtp_emailer.py
telegram_payment_bot/email/subscription_emailer.py
telegram_payment_bot/google/__init__.py
telegram_payment_bot/google/google_cred_types.py
telegram_payment_bot/google/google_sheet_opener.py
telegram_payment_bot/google/google_sheet_rows_getter.py
telegram_payment_bot/lang/lang_en.xml
telegram_payment_bot/logger/__init__.py
telegram_payment_bot/logger/logger.py
telegram_payment_bot/member/__init__.py
telegram_payment_bot/member/joined_members_checker.py
telegram_payment_bot/member/members_kicker.py
telegram_payment_bot/member/members_payment_getter.py
telegram_payment_bot/member/members_username_getter.py
telegram_payment_bot/message/__init__.py
telegram_payment_bot-0.8.0.dist-info/licenses/LICENSE
telegram_payment_bot-0.8.0.dist-info/METADATA
telegram_payment_bot-0.8.0.dist-info/WHEEL
telegram_payment_bot-0.8.0.dist-info/top_level.txt
telegram_payment_bot-0.8.0.dist-info/RECORD
