Metadata-Version: 2.4
Name: telegram_payment_bot
Version: 0.8.0
Summary: Telegram bot for managing payments
Author-email: Emanuele Bellocchia <ebellocchia@gmail.com>
Maintainer-email: Emanuele Bellocchia <ebellocchia@gmail.com>
License-Expression: MIT
Project-URL: Homepage, https://github.com/ebellocchia/telegram_payment_bot
Project-URL: Changelog, https://github.com/ebellocchia/telegram_payment_bot/blob/master/CHANGELOG.md
Project-URL: Repository, https://github.com/ebellocchia/telegram_payment_bot
Project-URL: Download, https://github.com/ebellocchia/telegram_payment_bot/archive/v{version}.tar.gz
Keywords: telegram,bot,telegram bot,payments,payments check
Classifier: Programming Language :: Python :: 3.7
Classifier: Programming Language :: Python :: 3.8
Classifier: Programming Language :: Python :: 3.9
Classifier: Programming Language :: Python :: 3.10
Classifier: Programming Language :: Python :: 3.11
Classifier: Programming Language :: Python :: 3.12
Classifier: Programming Language :: Python :: 3.13
Classifier: Development Status :: 5 - Production/Stable
Classifier: Operating System :: OS Independent
Classifier: Intended Audience :: Developers
Requires-Python: >=3.7
License-File: LICENSE
Requires-Dist: pygsheets
Requires-Dist: xlrd
Requires-Dist: openpyxl
Requires-Dist: pyrotgfork
Requires-Dist: pytgcrypto
Requires-Dist: aiosmtplib
Requires-Dist: aiofiles
Requires-Dist: apscheduler
Requires-Dist: defusedxml
Dynamic: license-file
